{
  "db_name": "PostgreSQL",
  "query": "SELECT id, code, item_id, version,\n                  status AS \"status: _\",\n                  created_at\n           FROM boms ORDER BY code",
  "describe": {
    "columns": [
      {
        "ordinal": 0,
        "name": "id",
        "type_info": "Uuid"
      },
      {
        "ordinal": 1,
        "name": "code",
        "type_info": "Text"
      },
      {
        "ordinal": 2,
        "name": "item_id",
        "type_info": "Uuid"
      },
      {
        "ordinal": 3,
        "name": "version",
        "type_info": "Int4"
      },
      {
        "ordinal": 4,
        "name": "status: _",
        "type_info": {
          "Custom": {
            "name": "bom_status",
            "kind": {
              "Enum": [
                "draft",
                "active",
                "under_review"
              ]
            }
          }
        }
      },
      {
        "ordinal": 5,
        "name": "created_at",
        "type_info": "Timestamptz"
      }
    ],
    "parameters": {
      "Left": []
    },
    "nullable": [
      false,
      false,
      false,
      false,
      false,
      false
    ]
  },
  "hash": "2e636373469dd65e6e5afaf19c0df2f053653bfcbc1e6047b273839fcd97a229"
}
