{
  "db_name": "PostgreSQL",
  "query": "SELECT id, po_id, item_id, qty_ordered, qty_received, unit_price, uom_id\n         FROM po_lines WHERE po_id = $1 ORDER BY id",
  "describe": {
    "columns": [
      {
        "ordinal": 0,
        "name": "id",
        "type_info": "Uuid"
      },
      {
        "ordinal": 1,
        "name": "po_id",
        "type_info": "Uuid"
      },
      {
        "ordinal": 2,
        "name": "item_id",
        "type_info": "Uuid"
      },
      {
        "ordinal": 3,
        "name": "qty_ordered",
        "type_info": "Numeric"
      },
      {
        "ordinal": 4,
        "name": "qty_received",
        "type_info": "Numeric"
      },
      {
        "ordinal": 5,
        "name": "unit_price",
        "type_info": "Numeric"
      },
      {
        "ordinal": 6,
        "name": "uom_id",
        "type_info": "Uuid"
      }
    ],
    "parameters": {
      "Left": [
        "Uuid"
      ]
    },
    "nullable": [
      false,
      false,
      false,
      false,
      false,
      false,
      false
    ]
  },
  "hash": "3e0ae5157641ae673f99b640b58683cd36cf7b19aad6ae269d24683d2c91c4a1"
}
